tuop/__init__.py
tuop/serpTriangle.py
tuop/sixth.py
tuop-0.0.1.dist-info/METADATA
tuop-0.0.1.dist-info/WHEEL
tuop-0.0.1.dist-info/RECORD
